{  "_embedded" : {    "trips" : [ {      "tripName" : "TPHCM_NhaTrang\n",      "departLoca" : "HO Chi MInh",      "desLoca" : "Nha Trang",      "departStation" : "Bến xe Miền Tây",      "busId" : 144,      "busBrand" : "Thanh Buoi",      "seatAvailable" : 60,      "price" : 350000,      "startDatetime" : 11717717,      "arrivalDatetime" : 166116661,      "_links" : {        "self" : {          "href" : "http://localhost:8081/trips/1"        },        "trip" : {          "href" : "http://localhost:8081/trips/1"        }      }    }, {      "tripName" : "NhaTrang_TPHCM\n",      "departLoca" : "Nha Trang",      "desLoca" : "\u001DTPHCM",      "departStation" : "45 Trần Phú",      "busId" : 145,      "busBrand" : "Thanh Buoi\n\n",      "seatAvailable" : 60,      "price" : 350000,      "startDatetime" : 15818515,      "arrivalDatetime" : 161616161,      "_links" : {        "self" : {          "href" : "http://localhost:8081/trips/2"        },        "trip" : {          "href" : "http://localhost:8081/trips/2"        }      }    }, {      "tripName" : "TPHCM_DaLat",      "departLoca" : "Thành phố Hồ Chí Minh",      "desLoca" : "Đà Lạt",      "departStation" : "Bến xe Miền Tây\n",      "busId" : 146,      "busBrand" : "Thành Bưởi",      "seatAvailable" : 30,      "price" : 350000,      "startDatetime" : 15515144,      "arrivalDatetime" : 155151511,      "_links" : {        "self" : {          "href" : "http://localhost:8081/trips/3"        },        "trip" : {          "href" : "http://localhost:8081/trips/3"        }      }    }, {      "tripName" : "VT_HCM",      "departLoca" : "Vũng Tàu",      "desLoca" : "Thành phố Hồ Chí Minh",      "departStation" : "103 Trần Hưng Đạo, Vũng Tàu",      "busId" : 147,      "busBrand" : "Thành Bưởi",      "seatAvailable" : 30,      "price" : 280000,      "startDatetime" : 51511515,      "arrivalDatetime" : 155151511,      "_links" : {        "self" : {          "href" : "http://localhost:8081/trips/4"        },        "trip" : {          "href" : "http://localhost:8081/trips/4"        }      }    } ]  },  "_links" : {    "self" : {      "href" : "http://localhost:8081/trips"    },    "profile" : {      "href" : "http://localhost:8081/profile/trips"    }  },  "page" : {    "size" : 20,    "totalElements" : 4,    "totalPages" : 1,    "number" : 0  }}